_pillow_heif.cpython-310-x86_64-linux-gnu.so
pillow_heif/HeifImagePlugin.py
pillow_heif/__init__.py
pillow_heif/_deffered_error.py
pillow_heif/_lib_info.py
pillow_heif/_version.py
pillow_heif/as_plugin.py
pillow_heif/constants.py
pillow_heif/heif.py
pillow_heif/misc.py
pillow_heif/options.py
pillow_heif.libs/libde265-28bee745.so
pillow_heif.libs/libgcc_s-0cd532bd.so.1
pillow_heif.libs/libheif-981fb9f5.so.1.20.2
pillow_heif.libs/libstdc++-5d72f927.so.6.0.33
pillow_heif.libs/libx265-696280bf.so.215
pillow_heif-1.1.1.dist-info/METADATA
pillow_heif-1.1.1.dist-info/WHEEL
pillow_heif-1.1.1.dist-info/top_level.txt
pillow_heif-1.1.1.dist-info/zip-safe
pillow_heif-1.1.1.dist-info/RECORD
pillow_heif-1.1.1.dist-info/licenses/LICENSE.txt
pillow_heif-1.1.1.dist-info/licenses/LICENSES_bundled.txt
