Metadata-Version: 2.4
Name: pillow_heif
Version: 1.1.1
Summary: Python interface for libheif library
Home-page: https://github.com/bigcat88/pillow_heif
Author: Alexander Piskun
Author-email: bigcat88@users.noreply.github.com
License: BSD-3-Clause
Project-URL: Documentation, https://pillow-heif.readthedocs.io
Project-URL: Source, https://github.com/bigcat88/pillow_heif
Project-URL: Changelog, https://github.com/bigcat88/pillow_heif/blob/master/CHANGELOG.md
Keywords: heif,heic,pillow
Classifier: Development Status :: 5 - Production/Stable
Classifier: Intended Audience :: Developers
Classifier: Topic :: Software Development
Classifier: Topic :: Software Development :: Libraries
Classifier: Topic :: Multimedia :: Graphics
Classifier: Topic :: Multimedia :: Graphics :: Graphics Conversion
Classifier: Programming Language :: Python :: 3
Classifier: Programming Language :: Python :: 3.9
Classifier: Programming Language :: Python :: 3.10
Classifier: Programming Language :: Python :: 3.11
Classifier: Programming Language :: Python :: 3.12
Classifier: Programming Language :: Python :: 3.13
Classifier: Programming Language :: Python :: Implementation :: CPython
Classifier: Programming Language :: Python :: Implementation :: PyPy
Classifier: License :: OSI Approved :: GNU General Public License v2 (GPLv2)
Classifier: Operating System :: MacOS :: MacOS X
Classifier: Operating System :: POSIX :: Linux
Classifier: Operating System :: Microsoft :: Windows
Requires-Python: >=3.9
License-File: LICENSE.txt
License-File: LICENSES_bundled.txt
Requires-Dist: pillow>=11.1.0
Provides-Extra: docs
Requires-Dist: sphinx>=4.4; extra == "docs"
Requires-Dist: sphinx-issues>=3.0.1; extra == "docs"
Requires-Dist: sphinx-rtd-theme>=1.0; extra == "docs"
Provides-Extra: tests-min
Requires-Dist: pytest; extra == "tests-min"
Requires-Dist: defusedxml; extra == "tests-min"
Requires-Dist: packaging; extra == "tests-min"
Provides-Extra: tests
Requires-Dist: pytest; extra == "tests"
Requires-Dist: defusedxml; extra == "tests"
Requires-Dist: packaging; extra == "tests"
Requires-Dist: numpy; extra == "tests"
Requires-Dist: pympler; extra == "tests"
Provides-Extra: dev
Requires-Dist: pytest; extra == "dev"
Requires-Dist: defusedxml; extra == "dev"
Requires-Dist: packaging; extra == "dev"
Requires-Dist: numpy; extra == "dev"
Requires-Dist: pympler; extra == "dev"
Requires-Dist: opencv-python==4.12.0.88; extra == "dev"
Requires-Dist: pre-commit; extra == "dev"
Requires-Dist: pylint; extra == "dev"
Requires-Dist: coverage; extra == "dev"
Requires-Dist: setuptools; extra == "dev"
Dynamic: license-file
